[{
	"Titre": "",
	"Media": "",
	"Contenu": "",
	"Lien":"http://www.deco.fr/deco-noel/photos-68470/",
	"Statut": "ouvert",
	"Couleur": "beige",
	"Jour":"03"
}, {
	"Titre": "",
	"Media": "",
	"Contenu": "",
	"Lien":"http://www.deco.fr/deco-noel/photos-68470/",
	"Statut": "ouvert",
	"Couleur": "marron",
	"Jour":"06"
}, {
	"Titre": "",
	"Media": "",
	"Contenu": "",
	"Lien":"http://www.deco.fr/deco-noel/photos-68470/",
	"Statut": "ouvert",
	"Couleur": "turquoise",
	"Jour":"09"
}, {
	"Titre": "",
	"Media": "",
	"Contenu": "",
	"Lien":"http://www.deco.fr/deco-noel/photos-68470/",
	"Statut": "ouvert",
	"Couleur": "beige",
	"Jour":"12"
}, {
	"Titre": "",
	"Media": "",
	"Contenu": "",
	"Lien":"http://www.deco.fr/deco-noel/photos-68470/",
	"Statut": "ouvert",
	"Couleur": "marron",
	"Jour":"15"
}, {
	"Titre": "",
	"Media": "",
	"Contenu": "",
	"Lien":"http://www.deco.fr/deco-noel/photos-68470/",
	"Statut": "ferme",
	"Couleur": "turquoise",
	"Jour":"18"
}, {
	"Titre": "",
	"Media": "",
	"Contenu": "",
	"Lien":"http://www.deco.fr/deco-noel/photos-68470/",
	"Statut": "ferme",
	"Couleur": "beige",
	"Jour":"21"
}, {
	"Titre": "",
	"Media": "",
	"Contenu": "",
	"Lien":"http://www.deco.fr/deco-noel/photos-68470/",
	"Statut": "ferme",
	"Couleur": "marron",
	"Jour":"24"
}, {
	"Titre": "",
	"Media": "<img src='images/media02.JPG'/>",
	"Contenu": "<h4>La maison à l’heure de Noël</h4><p>Le 1er décembre sonne le début des festivités ! Noël approche à grands pas et il est temps de décorer sa maison pour être prêt le jour J. Pour vous inspirer, nous vous proposons de découvrir des idées de décoration pour toute la maison.</p><h4>La maison mise en scène</h4><p>Dans cet intérieur, c'est tout le salon qui est à la fête avec une mise en scène au pied du sapin qui rappelle une forêt enchantée avec des cerfs comme objets déco. Dans le reste de la pièce, bougies et guirlandes peaufinent le décor.</p>",
	"Lien":"http://www.deco.fr/deco-noel/photos-68470/",
	"Statut": "ouvert",
	"Couleur": "turquoise",
	"Jour":"02"
}, {
	"Titre": "",
	"Media": "",
	"Contenu": "",
	"Lien":"http://www.deco.fr/deco-noel/photos-68470/",
	"Statut": "ouvert",
	"Couleur": "beige",
	"Jour":"05"
}, {
	"Titre": "",
	"Media": "",
	"Contenu": "",
	"Lien":"http://www.deco.fr/deco-noel/photos-68470/",
	"Statut": "ouvert",
	"Couleur": "marron",
	"Jour":"08"
}, {
	"Titre": "",
	"Media": "",
	"Contenu": "",
	"Lien":"http://www.deco.fr/deco-noel/photos-68470/",
	"Statut": "ouvert",
	"Couleur": "turquoise",
	"Jour":"11"
}, {
	"Titre": "",
	"Media": "",
	"Contenu": "",
	"Lien":"http://www.deco.fr/deco-noel/photos-68470/",
	"Statut": "ouvert",
	"Couleur": "beige",
	"Jour":"14"
}, {
	"Titre": "",
	"Media": "",
	"Contenu": "",
	"Lien":"http://www.deco.fr/deco-noel/photos-68470/",
	"Statut": "ferme",
	"Couleur": "marron",
	"Jour":"17"
}, {
	"Titre": "",
	"Media": "",
	"Contenu": "",
	"Lien":"http://www.deco.fr/deco-noel/photos-68470/",
	"Statut": "ferme",
	"Couleur": "turquoise",
	"Jour":"20"
}, {
	"Titre": "",
	"Media": "",
	"Contenu": "",
	"Lien":"http://www.deco.fr/deco-noel/photos-68470/",
	"Statut": "ferme",
	"Couleur": "beige",
	"Jour":"23"
}, {
	"Titre": "",
	"Media": "",
	"Contenu": "",
	"Lien":"http://www.deco.fr/deco-noel/photos-68470/",
	"Statut": "ouvert",
	"Couleur": "marron",
	"Jour":"01"
}, {
	"Titre": "",
	"Media": "",
	"Contenu": "",
	"Lien":"http://www.deco.fr/deco-noel/photos-68470/",
	"Statut": "ouvert",
	"Couleur": "turquoise",
	"Jour":"04"
}, {
	"Titre": "",
	"Media": "",
	"Contenu": "",
	"Lien":"http://www.deco.fr/deco-noel/photos-68470/",
	"Statut": "ouvert",
	"Couleur": "beige",
	"Jour":"07"
}, {
	"Titre": "",
	"Media": "",
	"Contenu": "",
	"Lien":"http://www.deco.fr/deco-noel/photos-68470/",
	"Statut": "ouvert",
	"Couleur": "marron",
	"Jour":"10"
}, {
	"Titre": "",
	"Media": "",
	"Contenu": "",
	"Lien":"http://www.deco.fr/deco-noel/photos-68470/",
	"Statut": "ouvert",
	"Couleur": "turquoise",
	"Jour":"13"
}, {
	"Titre": "",
	"Media": "",
	"Contenu": "",
	"Lien":"http://www.deco.fr/deco-noel/photos-68470/",
	"Statut": "ferme",
	"Couleur": "beige",
	"Jour":"16"
}, {
	"Titre": "",
	"Media": "",
	"Contenu": "",
	"Lien":"http://www.deco.fr/deco-noel/photos-68470/",
	"Statut": "ferme",
	"Couleur": "marron",
	"Jour":"19"
}, {
	"Titre": "",
	"Media": "",
	"Contenu": "",
	"Lien":"http://www.deco.fr/deco-noel/photos-68470/",
	"Statut": "ferme",
	"Couleur": "turquoise",
	"Jour":"22"
}]